mseep_oxylabs_mcp-0.6.4.dist-info/licenses/LICENSE
oxylabs_mcp/__init__.py
oxylabs_mcp/config.py
oxylabs_mcp/exceptions.py
oxylabs_mcp/url_params.py
oxylabs_mcp/utils.py
oxylabs_mcp/tools/__init__.py
oxylabs_mcp/tools/ai_studio.py
oxylabs_mcp/tools/scraper.py
mseep_oxylabs_mcp-0.6.4.dist-info/METADATA
mseep_oxylabs_mcp-0.6.4.dist-info/WHEEL
mseep_oxylabs_mcp-0.6.4.dist-info/entry_points.txt
mseep_oxylabs_mcp-0.6.4.dist-info/top_level.txt
mseep_oxylabs_mcp-0.6.4.dist-info/RECORD
