Metadata-Version: 2.4
Name: mseep-oxylabs-mcp
Version: 0.6.4
Summary: Oxylabs MCP server
Author-email: mseep <support@skydeck.ai>
License-Expression: MIT
Project-URL: Homepage, https://github.com/oxylabs/oxylabs-mcp
Project-URL: Repository, https://github.com/oxylabs/oxylabs-mcp
Classifier: Programming Language :: Python :: 3
Classifier: Programming Language :: Python :: 3.12
Classifier: Programming Language :: Python :: 3.13
Classifier: Development Status :: 4 - Beta
Classifier: Operating System :: OS Independent
Requires-Python: >=3.12
License-File: LICENSE
Requires-Dist: fastmcp>=2.11.3
Requires-Dist: httpx>=0.28.1
Requires-Dist: lxml<6,>=5.3.0
Requires-Dist: lxml-html-clean>=0.4.1
Requires-Dist: markdownify>=0.14.1
Requires-Dist: oxylabs-ai-studio>=0.2.12
Requires-Dist: pydantic>=2.10.5
Requires-Dist: pydantic-settings>=2.8.1
Dynamic: license-file
